memory_benchmark/__init__.py
memory_benchmark/datasets/__init__.py
memory_benchmark/llms/__init__.py
memory_benchmark/methods/__init__.py
memory_benchmark-0.0.1.dev0.dist-info/LICENSE
memory_benchmark-0.0.1.dev0.dist-info/METADATA
memory_benchmark-0.0.1.dev0.dist-info/WHEEL
memory_benchmark-0.0.1.dev0.dist-info/top_level.txt
memory_benchmark-0.0.1.dev0.dist-info/RECORD
