Metadata-Version: 2.1
Name: memory-benchmark
Version: 0.0.1.dev0
Summary: A unified benchmark framework for long-term memory
Home-page: https://github.com/memodb-io/memory-benchmark
Author: Memobase
Classifier: Programming Language :: Python :: 3
Classifier: License :: OSI Approved :: MIT License
Classifier: Operating System :: OS Independent
Requires-Python: >=3.11
License-File: LICENSE
Requires-Dist: openai
Requires-Dist: memobase
Requires-Dist: transformers
